crypto_tools/__init__.py
crypto_tools/crypto.py
cryptograph_tools-0.1.2.dist-info/METADATA
cryptograph_tools-0.1.2.dist-info/WHEEL
cryptograph_tools-0.1.2.dist-info/entry_points.txt
cryptograph_tools-0.1.2.dist-info/top_level.txt
cryptograph_tools-0.1.2.dist-info/RECORD
