Metadata-Version: 2.4
Name: cryptograph-tools
Version: 0.1.2
Summary:  outil de cryptographie
Author-email: Fidelia <fidelia1310@gmail.com>
Requires-Python: >=3.7
Requires-Dist: pyfiglet
Requires-Dist: rich
